{
    "configurations": [
        {
            "name": "Win32",
            "includePath": [
                "${workspaceFolder}/**",
                "${workspaceFolder}/24-I2C-Hard/Libraries/CMSIS",
                "${workspaceFolder}/24-I2C-Hard/Libraries/STM32F10x_StdPeriph_Driver/inc",
                "${workspaceFolder}/24-I2C-Hard/User",
                "${workspaceFolder}/24-I2C-Hard/User/i2c",
                "${workspaceFolder}/24-I2C-Hard/User/led",
                "${workspaceFolder}/24-I2C-Hard/User/usart",
                "${workspaceFolder}/24-I2C-Soft/Libraries/CMSIS",
                "${workspaceFolder}/24-I2C-Soft/Libraries/STM32F10x_StdPeriph_Driver/inc",
                "${workspaceFolder}/24-I2C-Soft/User",
                "${workspaceFolder}/24-I2C-Soft/User/i2c",
                "${workspaceFolder}/24-I2C-Soft/User/led",
                "${workspaceFolder}/24-I2C-Soft/User/usart"
            ],
            "defines": [
                "_DEBUG",
                "UNICODE",
                "_UNICODE"
            ],
            "compilerPath": "D:\\Embedded\\Toolchains\\mingw64\\bin\\gcc.exe",
            "cStandard": "c17",
            "cppStandard": "gnu++17",
            "intelliSenseMode": "windows-gcc-x64",
            "configurationProvider": "cmsis-csolution"
        }
    ],
    "version": 4
}